LICENSE
pyparsy/__init__.py
pyparsy/enum_types.py
pyparsy/exceptions/__init__.py
pyparsy/internal/__init__.py
pyparsy/utils.py
pyparsy/validator/__init__.py
pyparsy-0.2.6.dist-info/METADATA
pyparsy-0.2.6.dist-info/LICENSE
pyparsy-0.2.6.dist-info/WHEEL
pyparsy-0.2.6.dist-info/RECORD
