Metadata-Version: 2.1
Name: pyparsy
Version: 0.2.6
Summary: HTML parsing library using YAML definitions and XPath
Home-page: https://github.com/vkolev/parsy
License: MIT
Author: Vladimir Kolev
Author-email: vladimir.r.kolev@gmail.com
Requires-Python: >=3.9,<4.0
Classifier: Development Status :: 3 - Alpha
Classifier: Environment :: Web Environment
Classifier: License :: OSI Approved :: MIT License
Classifier: Programming Language :: Python :: 3
Classifier: Programming Language :: Python :: 3.9
Classifier: Programming Language :: Python :: 3.10
Classifier: Programming Language :: Python :: 3.11
Classifier: Topic :: Text Processing :: Markup :: HTML
Classifier: Topic :: Utilities
Requires-Dist: lxml (>=4.9.1,<5.0.0)
Requires-Dist: parsel (>=1.7.0,<2.0.0)
Requires-Dist: pyyaml (>=6.0,<7.0)
Requires-Dist: schema (>=0.7.5,<0.8.0)
Project-URL: Repository, https://github.com/vkolev/parsy
